django_github_storage/__init__.py
django_github_storage/storage.py
django_github_storage-1.0.2.dist-info/DESCRIPTION.rst
django_github_storage-1.0.2.dist-info/METADATA
django_github_storage-1.0.2.dist-info/RECORD
django_github_storage-1.0.2.dist-info/WHEEL
django_github_storage-1.0.2.dist-info/metadata.json
django_github_storage-1.0.2.dist-info/top_level.txt
